ip_location_pkg/__init__.py
ip_location_pkg/findAddress.py
ipaddress_finder_dsa-0.0.1.dist-info/LICENSE
ipaddress_finder_dsa-0.0.1.dist-info/METADATA
ipaddress_finder_dsa-0.0.1.dist-info/WHEEL
ipaddress_finder_dsa-0.0.1.dist-info/top_level.txt
ipaddress_finder_dsa-0.0.1.dist-info/RECORD
