Metadata-Version: 2.1
Name: ipaddress-finder-dsa
Version: 0.0.1
Summary: A package that allows you to get ip address, as well as country, city and region
Home-page: https://github.com/pypa/sampleproject
Author: Saeed Adetugboboh
Author-email: dadetugboboh1@gmail.com
Classifier: Programming Language :: Python :: 3
Classifier: License :: OSI Approved :: MIT License
Classifier: Operating System :: OS Independent
Requires-Python: >=3.6
License-File: LICENSE
